setup.py
angeutils/__init__.py
angeutils/common_utils.py
angeutils/config_accessor.py
angeutils/decorators.py
angeutils/format_utils.py
angeutils/logger.py
angeutils.egg-info/PKG-INFO
angeutils.egg-info/SOURCES.txt
angeutils.egg-info/dependency_links.txt
angeutils.egg-info/top_level.txt
testing/__init__.py
testing/test_config_accessor.py